tests/__init__.py
tests/test_udecimal.py
udecimal/__init__.py
udecimal/udecimal.py
udecimal-0.1.0.dist-info/LICENSE
udecimal-0.1.0.dist-info/METADATA
udecimal-0.1.0.dist-info/WHEEL
udecimal-0.1.0.dist-info/top_level.txt
udecimal-0.1.0.dist-info/RECORD
