Metadata-Version: 2.1
Name: udecimal
Version: 0.1.0
Summary: Пакет для работы с десятичными числами с учётом неопределённостей и ковариаций
Home-page: https://github.com/skyfet/udecimal
Author: Arthem Harutiunyan
Author-email: arthemharutiunyan@gmail.com
Classifier: Programming Language :: Python :: 3
Classifier: License :: OSI Approved :: MIT License
Classifier: Operating System :: OS Independent
Requires-Python: >=3.6
License-File: LICENSE
Requires-Dist: mpmath (>=1.2.1)
Provides-Extra: dev
Requires-Dist: pytest (>=6.0) ; extra == 'dev'
